adaptive_classifier/__init__.py
adaptive_classifier/classifier.py
adaptive_classifier/ewc.py
adaptive_classifier/memory.py
adaptive_classifier/models.py
adaptive_classifier/multilabel.py
adaptive_classifier/strategic.py
adaptive_classifier-0.1.2.dist-info/licenses/LICENSE
adaptive_classifier-0.1.2.dist-info/METADATA
adaptive_classifier-0.1.2.dist-info/WHEEL
adaptive_classifier-0.1.2.dist-info/top_level.txt
adaptive_classifier-0.1.2.dist-info/RECORD
