Metadata-Version: 2.4
Name: adaptive-classifier
Version: 0.1.2
Summary: A flexible, adaptive classification system for dynamic text classification
Home-page: https://github.com/codelion/adaptive-classifier
Author: codelion
Author-email: codelion@okyasoft.com
Project-URL: Bug Tracker, https://github.com/codelion/adaptive-classifier/issues
Classifier: Development Status :: 4 - Beta
Classifier: Intended Audience :: Science/Research
Classifier: License :: OSI Approved :: Apache Software License
Classifier: Operating System :: OS Independent
Classifier: Programming Language :: Python :: 3
Classifier: Programming Language :: Python :: 3.8
Classifier: Programming Language :: Python :: 3.9
Classifier: Programming Language :: Python :: 3.10
Classifier: Topic :: Scientific/Engineering :: Artificial Intelligence
Requires-Python: >=3.8
License-File: LICENSE
Requires-Dist: torch>=2.0.0
Requires-Dist: transformers>=4.30.0
Requires-Dist: safetensors>=0.3.1
Requires-Dist: faiss-cpu>=1.7.4
Requires-Dist: numpy>=1.24.0
Requires-Dist: tqdm>=4.65.0
Requires-Dist: setuptools>=65.0.0
Requires-Dist: wheel>=0.40.0
Requires-Dist: scikit-learn
Requires-Dist: huggingface_hub>=0.17.0
Requires-Dist: optimum[onnxruntime]>=1.14.0
Provides-Extra: test
Requires-Dist: pytest>=7.0.0; extra == "test"
Requires-Dist: pytest-cov>=4.0.0; extra == "test"
Requires-Dist: pytest-randomly>=3.12.0; extra == "test"
Requires-Dist: psutil; extra == "test"
Dynamic: author
Dynamic: author-email
Dynamic: classifier
Dynamic: description
Dynamic: description-content-type
Dynamic: home-page
Dynamic: license-file
Dynamic: project-url
Dynamic: provides-extra
Dynamic: requires-dist
Dynamic: requires-python
Dynamic: summary
